odoo/addons/stock_account_inventory_force_date/__init__.py
odoo/addons/stock_account_inventory_force_date/__manifest__.py
odoo/addons/stock_account_inventory_force_date/i18n/stock_account_inventory_force_date.pot
odoo/addons/stock_account_inventory_force_date/models/__init__.py
odoo/addons/stock_account_inventory_force_date/models/res_company.py
odoo/addons/stock_account_inventory_force_date/models/stock_inventory.py
odoo/addons/stock_account_inventory_force_date/models/stock_inventory_line.py
odoo/addons/stock_account_inventory_force_date/models/stock_move.py
odoo/addons/stock_account_inventory_force_date/models/stock_move_line.py
odoo/addons/stock_account_inventory_force_date/security/stock_account_inventory_force_date_security.xml
odoo/addons/stock_account_inventory_force_date/static/description/icon.png
odoo/addons/stock_account_inventory_force_date/tests/__init__.py
odoo/addons/stock_account_inventory_force_date/tests/test_stock_inventory_force_date.py
odoo/addons/stock_account_inventory_force_date/views/res_company_view.xml
odoo/addons/stock_account_inventory_force_date/views/stock_inventory_view.xml
odoo11_addon_stock_account_inventory_force_date-11.0.1.0.0.99.dev3.dist-info/METADATA
odoo11_addon_stock_account_inventory_force_date-11.0.1.0.0.99.dev3.dist-info/WHEEL
odoo11_addon_stock_account_inventory_force_date-11.0.1.0.0.99.dev3.dist-info/top_level.txt
odoo11_addon_stock_account_inventory_force_date-11.0.1.0.0.99.dev3.dist-info/RECORD
